{
    "0 GameObject Base": 
    {
        "0 vector m_Component": 
        {
            "0 Array Array": [
                {"0 pair data": 
                {
                    "0 int first": 4,
                    "0 PPtr<Component> second": 
                    {
                        "0 int m_FileID": 0,
                        "0 SInt64 m_PathID": 15250
                    }
                }},
                {"0 pair data": 
                {
                    "0 int first": 212,
                    "0 PPtr<Component> second": 
                    {
                        "0 int m_FileID": 0,
                        "0 SInt64 m_PathID": 21784
                    }
                }},
                {"0 pair data": 
                {
                    "0 int first": 114,
                    "0 PPtr<Component> second": 
                    {
                        "0 int m_FileID": 0,
                        "0 SInt64 m_PathID": 46528
                    }
                }},
                {"0 pair data": 
                {
                    "0 int first": 114,
                    "0 PPtr<Component> second": 
                    {
                        "0 int m_FileID": 0,
                        "0 SInt64 m_PathID": 52489
                    }
                }},
                {"0 pair data": 
                {
                    "0 int first": 114,
                    "0 PPtr<Component> second": 
                    {
                        "0 int m_FileID": 0,
                        "0 SInt64 m_PathID": 54398
                    }
                }},
                {"0 pair data": 
                {
                    "0 int first": 114,
                    "0 PPtr<Component> second": 
                    {
                        "0 int m_FileID": 0,
                        "0 SInt64 m_PathID": 42041
                    }
                }},
                {"0 pair data": 
                {
                    "0 int first": 82,
                    "0 PPtr<Component> second": 
                    {
                        "0 int m_FileID": 0,
                        "0 SInt64 m_PathID": 21064
                    }
                }},
                {"0 pair data": 
                {
                    "0 int first": 114,
                    "0 PPtr<Component> second": 
                    {
                        "0 int m_FileID": 0,
                        "0 SInt64 m_PathID": 47013
                    }
                }},
                {"0 pair data": 
                {
                    "0 int first": 114,
                    "0 PPtr<Component> second": 
                    {
                        "0 int m_FileID": 0,
                        "0 SInt64 m_PathID": 43814
                    }
                }},
                {"0 pair data": 
                {
                    "0 int first": 114,
                    "0 PPtr<Component> second": 
                    {
                        "0 int m_FileID": 0,
                        "0 SInt64 m_PathID": 47756
                    }
                }},
                {"0 pair data": 
                {
                    "0 int first": 114,
                    "0 PPtr<Component> second": 
                    {
                        "0 int m_FileID": 0,
                        "0 SInt64 m_PathID": 39554
                    }
                }},
                {"0 pair data": 
                {
                    "0 int first": 114,
                    "0 PPtr<Component> second": 
                    {
                        "0 int m_FileID": 0,
                        "0 SInt64 m_PathID": 49651
                    }
                }},
                {"0 pair data": 
                {
                    "0 int first": 114,
                    "0 PPtr<Component> second": 
                    {
                        "0 int m_FileID": 0,
                        "0 SInt64 m_PathID": 44815
                    }
                }},
                {"0 pair data": 
                {
                    "0 int first": 114,
                    "0 PPtr<Component> second": 
                    {
                        "0 int m_FileID": 0,
                        "0 SInt64 m_PathID": 40640
                    }
                }},
                {"0 pair data": 
                {
                    "0 int first": 114,
                    "0 PPtr<Component> second": 
                    {
                        "0 int m_FileID": 0,
                        "0 SInt64 m_PathID": 33242
                    }
                }}
            ]
        },
        "0 unsigned int m_Layer": 10,
        "1 string m_Name": "boss_undying_geomancer",
        "0 UInt16 m_Tag": 0,
        "0 bool m_IsActive": true
    }
}