{
    "0 GameObject Base": 
    {
        "0 vector m_Component": 
        {
            "0 Array Array": [
                {"0 pair data": 
                {
                    "0 int first": 224,
                    "0 PPtr<Component> second": 
                    {
                        "0 int m_FileID": 0,
                        "0 SInt64 m_PathID": 27695
                    }
                }},
                {"0 pair data": 
                {
                    "0 int first": 114,
                    "0 PPtr<Component> second": 
                    {
                        "0 int m_FileID": 0,
                        "0 SInt64 m_PathID": 38195
                    }
                }},
                {"0 pair data": 
                {
                    "0 int first": 114,
                    "0 PPtr<Component> second": 
                    {
                        "0 int m_FileID": 0,
                        "0 SInt64 m_PathID": 47822
                    }
                }},
                {"0 pair data": 
                {
                    "0 int first": 222,
                    "0 PPtr<Component> second": 
                    {
                        "0 int m_FileID": 0,
                        "0 SInt64 m_PathID": 25477
                    }
                }},
                {"0 pair data": 
                {
                    "0 int first": 114,
                    "0 PPtr<Component> second": 
                    {
                        "0 int m_FileID": 0,
                        "0 SInt64 m_PathID": 40510
                    }
                }},
                {"0 pair data": 
                {
                    "0 int first": 114,
                    "0 PPtr<Component> second": 
                    {
                        "0 int m_FileID": 0,
                        "0 SInt64 m_PathID": 31219
                    }
                }},
                {"0 pair data": 
                {
                    "0 int first": 114,
                    "0 PPtr<Component> second": 
                    {
                        "0 int m_FileID": 0,
                        "0 SInt64 m_PathID": 37636
                    }
                }},
                {"0 pair data": 
                {
                    "0 int first": 114,
                    "0 PPtr<Component> second": 
                    {
                        "0 int m_FileID": 0,
                        "0 SInt64 m_PathID": 42169
                    }
                }}
            ]
        },
        "0 unsigned int m_Layer": 0,
        "1 string m_Name": "it Attachment Poison Feetprints",
        "0 UInt16 m_Tag": 0,
        "0 bool m_IsActive": true
    }
}