{
    "0 GameObject Base": 
    {
        "0 vector m_Component": 
        {
            "0 Array Array": [
                {"0 pair data": 
                {
                    "0 int first": 4,
                    "0 PPtr<Component> second": 
                    {
                        "0 int m_FileID": 0,
                        "0 SInt64 m_PathID": 17786
                    }
                }},
                {"0 pair data": 
                {
                    "0 int first": 114,
                    "0 PPtr<Component> second": 
                    {
                        "0 int m_FileID": 0,
                        "0 SInt64 m_PathID": 29619
                    }
                }},
                {"0 pair data": 
                {
                    "0 int first": 114,
                    "0 PPtr<Component> second": 
                    {
                        "0 int m_FileID": 0,
                        "0 SInt64 m_PathID": 43589
                    }
                }},
                {"0 pair data": 
                {
                    "0 int first": 114,
                    "0 PPtr<Component> second": 
                    {
                        "0 int m_FileID": 0,
                        "0 SInt64 m_PathID": 35464
                    }
                }},
                {"0 pair data": 
                {
                    "0 int first": 114,
                    "0 PPtr<Component> second": 
                    {
                        "0 int m_FileID": 0,
                        "0 SInt64 m_PathID": 48438
                    }
                }},
                {"0 pair data": 
                {
                    "0 int first": 114,
                    "0 PPtr<Component> second": 
                    {
                        "0 int m_FileID": 0,
                        "0 SInt64 m_PathID": 35130
                    }
                }},
                {"0 pair data": 
                {
                    "0 int first": 114,
                    "0 PPtr<Component> second": 
                    {
                        "0 int m_FileID": 0,
                        "0 SInt64 m_PathID": 47957
                    }
                }},
                {"0 pair data": 
                {
                    "0 int first": 114,
                    "0 PPtr<Component> second": 
                    {
                        "0 int m_FileID": 0,
                        "0 SInt64 m_PathID": 33942
                    }
                }},
                {"0 pair data": 
                {
                    "0 int first": 114,
                    "0 PPtr<Component> second": 
                    {
                        "0 int m_FileID": 0,
                        "0 SInt64 m_PathID": 45177
                    }
                }},
                {"0 pair data": 
                {
                    "0 int first": 114,
                    "0 PPtr<Component> second": 
                    {
                        "0 int m_FileID": 0,
                        "0 SInt64 m_PathID": 57716
                    }
                }},
                {"0 pair data": 
                {
                    "0 int first": 114,
                    "0 PPtr<Component> second": 
                    {
                        "0 int m_FileID": 0,
                        "0 SInt64 m_PathID": 33252
                    }
                }},
                {"0 pair data": 
                {
                    "0 int first": 114,
                    "0 PPtr<Component> second": 
                    {
                        "0 int m_FileID": 0,
                        "0 SInt64 m_PathID": 56039
                    }
                }},
                {"0 pair data": 
                {
                    "0 int first": 114,
                    "0 PPtr<Component> second": 
                    {
                        "0 int m_FileID": 0,
                        "0 SInt64 m_PathID": 41748
                    }
                }},
                {"0 pair data": 
                {
                    "0 int first": 114,
                    "0 PPtr<Component> second": 
                    {
                        "0 int m_FileID": 0,
                        "0 SInt64 m_PathID": 39472
                    }
                }},
                {"0 pair data": 
                {
                    "0 int first": 114,
                    "0 PPtr<Component> second": 
                    {
                        "0 int m_FileID": 0,
                        "0 SInt64 m_PathID": 51513
                    }
                }},
                {"0 pair data": 
                {
                    "0 int first": 114,
                    "0 PPtr<Component> second": 
                    {
                        "0 int m_FileID": 0,
                        "0 SInt64 m_PathID": 31428
                    }
                }},
                {"0 pair data": 
                {
                    "0 int first": 114,
                    "0 PPtr<Component> second": 
                    {
                        "0 int m_FileID": 0,
                        "0 SInt64 m_PathID": 40275
                    }
                }},
                {"0 pair data": 
                {
                    "0 int first": 114,
                    "0 PPtr<Component> second": 
                    {
                        "0 int m_FileID": 0,
                        "0 SInt64 m_PathID": 54514
                    }
                }},
                {"0 pair data": 
                {
                    "0 int first": 114,
                    "0 PPtr<Component> second": 
                    {
                        "0 int m_FileID": 0,
                        "0 SInt64 m_PathID": 39580
                    }
                }},
                {"0 pair data": 
                {
                    "0 int first": 114,
                    "0 PPtr<Component> second": 
                    {
                        "0 int m_FileID": 0,
                        "0 SInt64 m_PathID": 50373
                    }
                }},
                {"0 pair data": 
                {
                    "0 int first": 114,
                    "0 PPtr<Component> second": 
                    {
                        "0 int m_FileID": 0,
                        "0 SInt64 m_PathID": 32021
                    }
                }},
                {"0 pair data": 
                {
                    "0 int first": 114,
                    "0 PPtr<Component> second": 
                    {
                        "0 int m_FileID": 0,
                        "0 SInt64 m_PathID": 36233
                    }
                }}
            ]
        },
        "0 unsigned int m_Layer": 0,
        "1 string m_Name": "WorldDungeonVolcano",
        "0 UInt16 m_Tag": 0,
        "0 bool m_IsActive": true
    }
}