[{"name":"Greater Piranha","alias":"monster_piranha_hardmode","description":"Description for Greater Piranha","isBoss":false,"isElite":false,"isSetPieceMonster":false,"weapons":[{"name":"piranha_projectile","data":[{"projectile":{"name":"piranha_projectile","projectileName":"Projectile","speed":15,"damage":0,"damageMultiplier":1,"essenceDamageMultiplier":2,"range":1.5,"useTargetForRange":false,"useRandomRange":false,"maxHits":1,"arcSeparation":5,"maxLifetime":8,"rageMultiplier":1,"bounceBetweenEnemies":false,"pierceWorld":false,"color":{"r":0,"g":0,"b":0,"a":0}}}]}],"data":[{"sprite":{"name":"beast_piranha","baseSize":{"width":192,"height":144},"textureRectangle":{"x":4,"y":96,"width":38,"height":17},"textureOffset":{"x":4,"y":0},"color":{"r":1,"g":1,"b":1,"a":1}}},{"bSlide":true,"bEnemy":true},{"stats":[{"key":"Level","equation":"","value":29},{"key":"HealthMax","equation":"","value":15625},{"key":"DamageBonus","equation":"","value":320},{"key":"Tier","equation":"","value":9},{"key":"Experience","equation":"","value":400},{"key":"CriticalDefense","equation":"([Level]*[Level])*0.2 + 25","value":0},{"key":"Accuracy","equation":"([Level]*[Level])*0.4 + 150","value":0}]},{"loot":{"inheritedLootTable":{"name":"CommonLoot T9"},"guaranteeItemCount":0,"maximumItemCount":0,"lootTable":[{"item":"Enriched Leather","count":{"dice":0,"faces":0,"add":1},"chance":10,"allowModifiers":true}]}},{"sound":{"soundType":"Impact","sounds":["EnemyImpactGeneral1","EnemyImpactGeneral2","EnemyImpactGeneral3","EnemyImpactGeneral4","EnemyImpactGeneral5"]}},{"sound":{"soundType":"Wake","sounds":["PiranhaTypeWake1","PiranhaTypeWake2","PiranhaTypeWake3","PiranhaTypeWake4","PiranhaTypeWake5"]}},{"sound":{"soundType":"Pain","sounds":["PiranhaTypePain1","PiranhaTypePain2","PiranhaTypePain3","PiranhaTypePain4","PiranhaTypePain5"]}},{"sound":{"soundType":"Death","sounds":["PiranhaTypeDeath1","PiranhaTypeDeath2","PiranhaTypeDeath3","PiranhaTypeDeath4","PiranhaTypeDeath5"]}}],"zenithEffects":[],"category":"Beast","element":"None"}]